caramelize/__init__.py
caramelize-0.0.1.dist-info/LICENSE
caramelize-0.0.1.dist-info/METADATA
caramelize-0.0.1.dist-info/WHEEL
caramelize-0.0.1.dist-info/top_level.txt
caramelize-0.0.1.dist-info/RECORD
