Metadata-Version: 2.1
Name: caramelize
Version: 0.0.1
Summary: Caramel client
Home-page: https://github.com/caramelize.org/client
Author: Caramel
Author-email: pypi@caramelize.org
License: UNKNOWN
Platform: UNKNOWN
Classifier: Programming Language :: Python :: 3
Classifier: License :: OSI Approved :: MIT License
Classifier: Operating System :: OS Independent
Requires-Python: >=3.8
License-File: LICENSE
